faas/__init__.py
faas/core/__init__.py
faas/core/configuration.py
faas/core/faas_api_client.py
faas_sdk-1.0.1.dist-info/METADATA
faas_sdk-1.0.1.dist-info/WHEEL
faas_sdk-1.0.1.dist-info/top_level.txt
faas_sdk-1.0.1.dist-info/RECORD
